lacibus/__init__.py
lacibus/soda.py
lacibus-1.0.3.dist-info/LICENSE
lacibus-1.0.3.dist-info/METADATA
lacibus-1.0.3.dist-info/WHEEL
lacibus-1.0.3.dist-info/top_level.txt
lacibus-1.0.3.dist-info/RECORD
